jsondataclass/__init__.py
jsondataclass/config.py
jsondataclass/exceptions.py
jsondataclass/field.py
jsondataclass/mapper.py
jsondataclass/serializers.py
jsondataclass/typing.py
jsondataclass/utils.py
jsondataclass-0.3.0.dist-info/LICENSE
jsondataclass-0.3.0.dist-info/METADATA
jsondataclass-0.3.0.dist-info/WHEEL
jsondataclass-0.3.0.dist-info/top_level.txt
jsondataclass-0.3.0.dist-info/RECORD
