Metadata-Version: 2.1
Name: jsondataclass
Version: 0.3.0
Summary: Json dataclass mapper
Home-page: https://github.com/tushkanin/jsondataclass
Author: Aleksey Shulga
Author-email: oleksii.shulga@gmail.com
License: MIT license
Keywords: jsondataclass dataclasses json
Platform: UNKNOWN
Classifier: Development Status :: 4 - Beta
Classifier: Intended Audience :: Developers
Classifier: License :: OSI Approved :: MIT License
Classifier: Natural Language :: English
Classifier: Programming Language :: Python
Classifier: Programming Language :: Python :: 3.7
Classifier: Topic :: Software Development :: Libraries :: Python Modules
Requires-Python: >=3.7
